httpie_nifcloud_authv4.py
httpie_nifcloud_authv4-0.1.0.dist-info/entry_points.txt
httpie_nifcloud_authv4-0.1.0.dist-info/LICENSE
httpie_nifcloud_authv4-0.1.0.dist-info/WHEEL
httpie_nifcloud_authv4-0.1.0.dist-info/METADATA
httpie_nifcloud_authv4-0.1.0.dist-info/RECORD
