Metadata-Version: 2.1
Name: httpie-nifcloud-authv4
Version: 0.1.0
Summary: AWS/NIFCLOUD Auth v4 plugin for HTTPie
Home-page: https://github.com/kzmake/httpie-nifcloud-authv4
License: MIT
Keywords: httpie,nifcloud,aws,plugin,auth
Author: kzmake
Author-email: kzmake.i3a@gmail.com
Requires-Python: >=3.6,<4.0
Classifier: Development Status :: 4 - Beta
Classifier: Environment :: Plugins
Classifier: License :: OSI Approved :: MIT License
Classifier: Programming Language :: Python
Classifier: Programming Language :: Python :: 3
Classifier: Programming Language :: Python :: 3.6
Classifier: Programming Language :: Python :: 3.7
Classifier: Programming Language :: Python :: 3.8
Classifier: Topic :: Internet :: WWW/HTTP
Classifier: Topic :: Utilities
Requires-Dist: aws-requests-auth (>=0.4.2,<0.5.0)
Requires-Dist: httpie (>=2.0.0,<3.0.0)
Project-URL: Repository, https://github.com/kzmake/httpie-nifcloud-authv4
